gitlab_ps_utils/__init__.py
gitlab_ps_utils/api.py
gitlab_ps_utils/audit_logger.py
gitlab_ps_utils/base_config.py
gitlab_ps_utils/decorators.py
gitlab_ps_utils/dict_utils.py
gitlab_ps_utils/exceptions.py
gitlab_ps_utils/file_utils.py
gitlab_ps_utils/gitlab_utils.py
gitlab_ps_utils/json_utils.py
gitlab_ps_utils/jsondiff.py
gitlab_ps_utils/list_utils.py
gitlab_ps_utils/logger.py
gitlab_ps_utils/misc_utils.py
gitlab_ps_utils/process.py
gitlab_ps_utils/processes.py
gitlab_ps_utils/string_utils.py
gitlab_ps_utils/xml_utils.py
gitlab_ps_utils-0.17.0.dist-info/METADATA
gitlab_ps_utils-0.17.0.dist-info/WHEEL
gitlab_ps_utils-0.17.0.dist-info/licenses/LICENSE
gitlab_ps_utils-0.17.0.dist-info/RECORD
