Metadata-Version: 2.4
Name: gitlab-ps-utils
Version: 0.17.0
Summary: Shared python utilities used by GitLab Professional Services tooling
License: MIT
License-File: LICENSE
Author: GitLab Professional Services
Author-email: proserv@gitlab.com
Requires-Python: >=3.10
Classifier: License :: OSI Approved :: MIT License
Classifier: Programming Language :: Python :: 3
Classifier: Programming Language :: Python :: 3.10
Classifier: Programming Language :: Python :: 3.11
Classifier: Programming Language :: Python :: 3.12
Classifier: Programming Language :: Python :: 3.13
Classifier: Programming Language :: Python :: 3.14
Requires-Dist: httpx (>=0.28.1,<0.29.0)
Requires-Dist: requests (>=2.32.5,<3.0.0)
Requires-Dist: tqdm (>=4.61.0,<5.0.0)
Requires-Dist: xmltodict (>=0.12.0,<0.13.0)
Project-URL: Homepage, https://gitlab.com/gitlab-org/professional-services-automation/gitlab-ps-utils
